[{"model": "user.message", "pk": 47, "fields": {"dialog": 1, "author": 17, "message": "rerer", "created_date": "2023-02-24T10:21:06.441Z", "is_readed": true}}, {"model": "user.message", "pk": 48, "fields": {"dialog": 1, "author": 17, "message": "trtrt", "created_date": "2023-02-24T10:25:48.433Z", "is_readed": true}}, {"model": "user.message", "pk": 49, "fields": {"dialog": 3, "author": 1, "message": "yututyu", "created_date": "2023-02-24T10:36:25.175Z", "is_readed": false}}, {"model": "user.message", "pk": 50, "fields": {"dialog": 3, "author": 1, "message": "trtr", "created_date": "2023-02-24T10:38:09.812Z", "is_readed": false}}, {"model": "user.message", "pk": 51, "fields": {"dialog": 3, "author": 1, "message": "gfgfg", "created_date": "2023-02-24T10:48:19.311Z", "is_readed": false}}, {"model": "user.message", "pk": 52, "fields": {"dialog": 3, "author": 1, "message": "htfhf", "created_date": "2023-02-24T10:52:37.947Z", "is_readed": false}}]